gtfinder/ExtensiveFormGame.py
gtfinder/InformationSet.py
gtfinder/Node.py
gtfinder/__init__.py
gtfinder-1.1.3.dist-info/LICENSE.txt
gtfinder-1.1.3.dist-info/METADATA
gtfinder-1.1.3.dist-info/WHEEL
gtfinder-1.1.3.dist-info/top_level.txt
gtfinder-1.1.3.dist-info/RECORD
