Metadata-Version: 2.1
Name: gtfinder
Version: 1.1.3
Summary: A package to create and analyze dynamic games
Home-page: https://github.com/ettoredangelo/gtfinder
Author: Ettore d'Angelo
Author-email: ettoredangelo97@gmail.com
License: UNKNOWN
Platform: UNKNOWN
Classifier: Programming Language :: Python :: 3
Classifier: License :: OSI Approved :: MIT License
Classifier: Operating System :: OS Independent
Requires-Dist: numpy
Requires-Dist: scipy
